cdk_github_import/__init__.py
cdk_github_import/py.typed
cdk_github_import/_jsii/__init__.py
cdk_github_import/_jsii/cdk-github-import@1.0.0.jsii.tgz
cdk_github_import-1.0.0.dist-info/METADATA
cdk_github_import-1.0.0.dist-info/WHEEL
cdk_github_import-1.0.0.dist-info/top_level.txt
cdk_github_import-1.0.0.dist-info/RECORD
