Metadata-Version: 2.1
Name: cdk-github-import
Version: 1.0.0
Summary: Import local file assets into a new Github repository
Home-page: https://github.com/pahud/cdk-github-import.git
Author: Pahud Hsieh<hunhsieh@amazon.com>
License: Apache-2.0
Project-URL: Source, https://github.com/pahud/cdk-github-import.git
Platform: UNKNOWN
Classifier: Intended Audience :: Developers
Classifier: Operating System :: OS Independent
Classifier: Programming Language :: JavaScript
Classifier: Programming Language :: Python :: 3 :: Only
Classifier: Programming Language :: Python :: 3.6
Classifier: Programming Language :: Python :: 3.7
Classifier: Programming Language :: Python :: 3.8
Classifier: Typing :: Typed
Classifier: Development Status :: 4 - Beta
Classifier: License :: OSI Approved
Requires-Python: >=3.6
Requires-Dist: jsii (<2.0.0,>=1.6.0)
Requires-Dist: publication (>=0.0.3)
Requires-Dist: aws-cdk.aws-codestar (<2.0.0,>=1.45.0)
Requires-Dist: aws-cdk.aws-s3 (<2.0.0,>=1.45.0)
Requires-Dist: aws-cdk.aws-s3-assets (<2.0.0,>=1.45.0)
Requires-Dist: aws-cdk.core (<2.0.0,>=1.45.0)
Requires-Dist: constructs (<4.0.0,>=3.0.3)
